pyjwt512/CreateJwtToken.py
pyjwt512/Es512KeysManger.py
pyjwt512/Exceptions.py
pyjwt512/VerifyJwtToken.py
pyjwt512/__init__.py
pyjwt512/genjwt.py
pyjwt512-0.1.18.dist-info/LICENSE
pyjwt512-0.1.18.dist-info/METADATA
pyjwt512-0.1.18.dist-info/WHEEL
pyjwt512-0.1.18.dist-info/entry_points.txt
pyjwt512-0.1.18.dist-info/RECORD
