Metadata-Version: 2.1
Name: PyJwt512
Version: 0.1.18
Summary: Simple JWT Manager for ES512
Author: Lubomir Spacek
Author-email: hexim@hexim.cz
Requires-Python: >=3.10,<4.0
Classifier: License :: OSI Approved :: MIT License
Classifier: Programming Language :: Python :: 3
Classifier: Programming Language :: Python :: 3.10
Classifier: Programming Language :: Python :: 3.11
Classifier: Programming Language :: Python :: 3.12
Requires-Dist: cryptography (>=41.0.7,<42.0.0)
Requires-Dist: fire (>=0.5.0,<0.6.0)
Requires-Dist: pyjwt (>=2.8.0,<3.0.0)
Project-URL: Homepage, https://github.com/heximcz/pyjwt512
Project-URL: Issues, https://github.com/heximcz/pyjwt512/issues
